{
  "source": "https://thehackernews.com/feeds/posts/default?alt=rss",
  "updated": "2026-03-15T17:18:30Z",
  "items": [
    {
      "title": "OpenClaw AI Agent Flaws Could Enable Prompt Injection and Data Exfiltration",
      "link": "https://thehackernews.com/2026/03/openclaw-ai-agent-flaws-could-enable.html",
      "pubDate": "Sat, 14 Mar 2026 21:47:00 +0530"
    },
    {
      "title": "GlassWorm Supply-Chain Attack Abuses 72 Open VSX Extensions to Target Developers",
      "link": "https://thehackernews.com/2026/03/glassworm-supply-chain-attack-abuses-72.html",
      "pubDate": "Sat, 14 Mar 2026 18:25:00 +0530"
    },
    {
      "title": "Chinese Hackers Target Southeast Asian Militaries with AppleChris and MemFun Malware",
      "link": "https://thehackernews.com/2026/03/chinese-hackers-target-southeast-asian.html",
      "pubDate": "Fri, 13 Mar 2026 23:03:00 +0530"
    },
    {
      "title": "Meta to Shut Down Instagram End-to-End Encrypted Chat Support Starting May 2026",
      "link": "https://thehackernews.com/2026/03/meta-to-shut-down-instagram-end-to-end.html",
      "pubDate": "Fri, 13 Mar 2026 22:39:00 +0530"
    },
    {
      "title": "INTERPOL Dismantles 45,000 Malicious IPs, Arrests 94 in Global Cybercrime",
      "link": "https://thehackernews.com/2026/03/interpol-dismantles-45000-malicious-ips.html",
      "pubDate": "Fri, 13 Mar 2026 20:50:00 +0530"
    },
    {
      "title": "Storm-2561 Spreads Trojan VPN Clients via SEO Poisoning to Steal Credentials",
      "link": "https://thehackernews.com/2026/03/storm-2561-spreads-trojan-vpn-clients.html",
      "pubDate": "Fri, 13 Mar 2026 19:08:00 +0530"
    },
    {
      "title": "Investigating a New Click-Fix Variant",
      "link": "https://thehackernews.com/2026/03/investigating-new-click-fix-variant.html",
      "pubDate": "Fri, 13 Mar 2026 18:58:00 +0530"
    },
    {
      "title": "Google Fixes Two Chrome Zero-Days Exploited in the Wild Affecting Skia and V8",
      "link": "https://thehackernews.com/2026/03/google-fixes-two-chrome-zero-days.html",
      "pubDate": "Fri, 13 Mar 2026 14:47:00 +0530"
    },
    {
      "title": "Nine CrackArmor Flaws in Linux AppArmor Enable Root Escalation, Bypass Container Isolation",
      "link": "https://thehackernews.com/2026/03/nine-crackarmor-flaws-in-linux-apparmor.html",
      "pubDate": "Fri, 13 Mar 2026 13:48:00 +0530"
    },
    {
      "title": "Authorities Disrupt SocksEscort Proxy Botnet Exploiting 369,000 IPs Across 163 Countries",
      "link": "https://thehackernews.com/2026/03/authorities-disrupt-socksescort-proxy.html",
      "pubDate": "Fri, 13 Mar 2026 10:56:00 +0530"
    },
    {
      "title": "Veeam Patches 7 Critical Backup & Replication Flaws Allowing Remote Code Execution",
      "link": "https://thehackernews.com/2026/03/veeam-patches-7-critical-backup.html",
      "pubDate": "Fri, 13 Mar 2026 09:45:00 +0530"
    },
    {
      "title": "Rust-Based VENON Malware Targets 33 Brazilian Banks with Credential-Stealing Overlays",
      "link": "https://thehackernews.com/2026/03/rust-based-venon-malware-targets-33.html",
      "pubDate": "Thu, 12 Mar 2026 23:01:00 +0530"
    }
  ]
}